spys/__init__.py
spys/filters.py
spys/me.py
spys/one.py
spys/proxy_view.py
spys-1.1.0.dist-info/METADATA
spys-1.1.0.dist-info/WHEEL
spys-1.1.0.dist-info/top_level.txt
spys-1.1.0.dist-info/RECORD
