Metadata-Version: 2.1
Name: spys
Version: 1.1.0
Summary: Python API for spys.one/spys.me proxies
Home-page: https://github.com/NIKDISSV-Forever/PySpysAPI
Author: Nikita (NIKDISSV)
Author-email: nikdissv@proton.me
Classifier: Programming Language :: Python :: 3
Classifier: License :: OSI Approved :: MIT License
Classifier: Operating System :: OS Independent
Classifier: Typing :: Typed
Classifier: Development Status :: 4 - Beta
Classifier: Environment :: Console
Requires-Python: >=3.8
Requires-Dist: bs4
Requires-Dist: httpx
Requires-Dist: lxml ; python_version < "3.11"
